{"version":1,"resource":"vscode-remote://ssh-remote%2B7b22686f73744e616d65223a226b6176696e434f4d50555441227d/home/kavin/dockerfiles/CS490container/html/portal/t/CreateQuiz.html","entries":[{"id":"o8Xn.html","timestamp":1649008109228},{"id":"Amva.html","timestamp":1649096832318},{"id":"jKAi.html","timestamp":1649096975695},{"id":"n2vx.html","timestamp":1649097087496},{"id":"X5lS.html","timestamp":1649097103008},{"id":"XwPk.html","timestamp":1649184885018},{"id":"vQZD.html","source":"undoRedo.source","timestamp":1649184926286},{"id":"NQWw.html","timestamp":1649184985914},{"id":"Peie.html","timestamp":1649196594541},{"id":"wI36.html","timestamp":1649196647277},{"id":"Xkpz.html","timestamp":1649196835241},{"id":"mgSk.html","timestamp":1649197263499},{"id":"JFQo.html","timestamp":1649197383432},{"id":"XU43.html","timestamp":1649198728873},{"id":"ZGj5.html","timestamp":1649201225104},{"id":"lDrO.html","timestamp":1649268017285},{"id":"NhpZ.html","timestamp":1649268253950},{"id":"Chmz.html","timestamp":1649434410880},{"id":"bCgA.html","timestamp":1649457873369},{"id":"1c7c.html","timestamp":1649457893129},{"id":"J7VK.html","source":"undoRedo.source","timestamp":1649457913702},{"id":"SdyI.html","timestamp":1649523255996},{"id":"Ioqj.html","timestamp":1649528666783},{"id":"N1rS.html","source":"undoRedo.source","timestamp":1649528673879},{"id":"u4JE.html","timestamp":1650396876894}]}