{"version":1,"resource":"vscode-remote://ssh-remote%2B7b22686f73744e616d65223a226b6176696e434f4d50555441227d/home/kavin/dockerfiles/CS490container/html/portal/s/TakeQuiz.html","entries":[{"id":"0zxy.html","timestamp":1649008100400},{"id":"vorI.html","timestamp":1649526780555},{"id":"WY9m.html","timestamp":1649526794183},{"id":"xtr0.html","timestamp":1649526833103},{"id":"8ezC.html","timestamp":1649526871371},{"id":"O72v.html","timestamp":1649526901143},{"id":"ZHEQ.html","timestamp":1649527000992},{"id":"0TO4.html","timestamp":1649527475603},{"id":"5U5q.html","timestamp":1650397038692},{"id":"yH1i.html","timestamp":1650397540237},{"id":"UNLT.html","timestamp":1650397569901},{"id":"PAG2.html","timestamp":1650397586142},{"id":"Yion.html","source":"undoRedo.source","timestamp":1650397592018},{"id":"nRPG.html","timestamp":1650397715167}]}